setup.cfg
setup.py
pm.py.egg-info/PKG-INFO
pm.py.egg-info/SOURCES.txt
pm.py.egg-info/dependency_links.txt
pm.py.egg-info/entry_points.txt
pm.py.egg-info/requires.txt
pm.py.egg-info/top_level.txt
pypm/__init__.py
pypm/__main__.py
pypm/pypm.py