Metadata-Version: 1.1
Name: pm.py
Version: 2.0b4
Summary: Post-mortem debugging for Python programs
Home-page: https://github.com/onna/pypm
Author: Jordi Masip
Author-email: jordi.masip@onna.com
License: MIT
Platform: UNKNOWN
Classifier: Development Status :: 4 - Beta
Classifier: Environment :: Console
Classifier: Intended Audience :: Developers
Classifier: License :: OSI Approved :: MIT License
Classifier: Natural Language :: English
Classifier: Operating System :: OS Independent
Classifier: Programming Language :: Python
Classifier: Topic :: Software Development :: Debuggers
